{
  "images": [
    {
      "filename": "image0.png",
      "filepath": "images/image0.png",
      "timestamp": "2025-02-26T15:47:02Z",
      "author": "クロム",
      "width": 1920,
      "height": 1080,
      "aspect_ratio": 1.778
    },
    {
      "filename": "image1.png",
      "filepath": "images/image1.png",
      "timestamp": "2025-11-04T07:43:48Z",
      "author": "ZX",
      "width": 1152,
      "height": 2048,
      "aspect_ratio": 0.562
    },
    {
      "filename": "image2.png",
      "filepath": "images/image2.png",
      "timestamp": "2025-10-27T00:08:33Z",
      "author": "@ΣПΛ$",
      "width": 1152,
      "height": 2048,
      "aspect_ratio": 0.562
    },
    {
      "filename": "image3.png",
      "filepath": "images/image3.png",
      "timestamp": "2025-09-28T12:33:12Z",
      "author": "ふぃーぬ",
      "width": 2048,
      "height": 1152,
      "aspect_ratio": 1.778
    },
    {
      "filename": "image4.png",
      "filepath": "images/image4.png",
      "timestamp": "2026-01-22T03:35:08Z",
      "author": "Jhin",
      "width": 1080,
      "height": 1920,
      "aspect_ratio": 0.562
    },
    {
      "filename": "image5.png",
      "filepath": "images/image5.png",
      "timestamp": "2025-10-08T15:11:33Z",
      "author": "Alpha63",
      "width": 2048,
      "height": 1152,
      "aspect_ratio": 1.778
    },
    {
      "filename": "image6.png",
      "filepath": "images/image6.png",
      "timestamp": "2025-03-04T03:22:15Z",
      "author": "ｳﾆﾃｨ",
      "width": 1080,
      "height": 1920,
      "aspect_ratio": 0.562
    },
    {
      "filename": "image7.png",
      "filepath": "images/image7.png",
      "timestamp": "2025-06-10T04:13:58Z",
      "author": "J_B_Old+soul",
      "width": 1920,
      "height": 1080,
      "aspect_ratio": 1.778
    },
    {
      "filename": "image8.png",
      "filepath": "images/image8.png",
      "timestamp": "2024-11-29T16:49:25Z",
      "author": "ぜふぁ太郎",
      "width": 2048,
      "height": 1152,
      "aspect_ratio": 1.778
    },
    {
      "filename": "image9.png",
      "filepath": "images/image9.png",
      "timestamp": "2025-10-06T15:57:42Z",
      "author": "なお",
      "width": 1920,
      "height": 1080,
      "aspect_ratio": 1.778
    },
    {
      "filename": "image10.png",
      "filepath": "images/image10.png",
      "timestamp": "2025-10-03T15:04:00Z",
      "author": "ウェゴート",
      "width": 1920,
      "height": 1080,
      "aspect_ratio": 1.778
    },
    {
      "filename": "image11.png",
      "filepath": "images/image11.png",
      "timestamp": "2025-09-08T04:40:50Z",
      "author": "プロトタイプ(Prototype)",
      "width": 1152,
      "height": 2048,
      "aspect_ratio": 0.562
    },
    {
      "filename": "image12.png",
      "filepath": "images/image12.png",
      "timestamp": "2025-05-20T18:14:30Z",
      "author": "Mafty Naveyu Erin",
      "width": 1152,
      "height": 2048,
      "aspect_ratio": 0.562
    }
  ],
  "created_at": "2026-01-29T13:24:23Z"
}